django_payments_flow/__init__.py
django_payments_flow/provider.py
django_payments_flow/version.py
django_payments_flow-0.1.4.dist-info/LICENSE
django_payments_flow-0.1.4.dist-info/METADATA
django_payments_flow-0.1.4.dist-info/WHEEL
django_payments_flow-0.1.4.dist-info/RECORD
