Metadata-Version: 2.1
Name: django-payments-flow
Version: 0.1.4
Summary: Soporte Flow para Django Payments
Home-page: https://mariofix.github.io/django-payments-flow/
License: MIT
Keywords: flow,pagos,django,payment,django-payments
Author: Mario Hernandez
Author-email: mariofix@proton.me
Requires-Python: >=3.8.10,<4.0.0
Classifier: Development Status :: 4 - Beta
Classifier: Framework :: Django
Classifier: Intended Audience :: Developers
Classifier: Intended Audience :: Information Technology
Classifier: License :: OSI Approved :: MIT License
Classifier: Operating System :: OS Independent
Classifier: Programming Language :: Python :: 3
Classifier: Programming Language :: Python :: 3.9
Classifier: Programming Language :: Python :: 3.10
Classifier: Programming Language :: Python :: 3.11
Classifier: Programming Language :: Python :: 3.8
Classifier: Topic :: Software Development :: Libraries :: Python Modules
Requires-Dist: django-payments (>=2.0,<3.0)
Requires-Dist: pyflowcl (>=1.2,<2.0)
Project-URL: Documentation, https://mariofix.github.io/django-payments-flow/
Project-URL: Repository, https://github.com/mariofix/django-payments-flow
